biodb/__init__.py
biodb-0.0.1.dist-info/LICENSE
biodb-0.0.1.dist-info/METADATA
biodb-0.0.1.dist-info/WHEEL
biodb-0.0.1.dist-info/top_level.txt
biodb-0.0.1.dist-info/RECORD
