Metadata-Version: 2.1
Name: biodb
Version: 0.0.1
Summary: Computational alchemy; Django ORM for Neo4J chemistry models.
Home-page: https://github.com/HashRocketSyntax/biodb
Author: Layne Sadler
Author-email: layne.sadler@gmail.com
License: UNKNOWN
Platform: UNKNOWN
Classifier: Programming Language :: Python :: 3
Classifier: License :: OSI Approved :: MIT License
Classifier: Operating System :: OS Independent
